[{"line":2,"elements":[{"line":7,"name":"","description":"","type":"background","keyword":"Antecedentes","steps":[{"result":{"duration":3720171000,"status":"passed"},"line":8,"name":"que el usuario navega a la página principal de jQuery Datepicker","match":{"location":"com.sqa.datepicker.stepdefinitions.DatepickerStepDefinitions.queElUsuarioNavegaALaPaginaPrincipalDeJQueryDatepicker()"},"keyword":"Dado "}]},{"start_timestamp":"2025-10-06T08:27:12.485Z","before":[{"result":{"duration":16038000,"status":"passed"},"match":{"location":"com.sqa.datepicker.stepdefinitions.DatepickerStepDefinitions.setUp()"}}],"line":11,"name":"Reserva de una cita seleccionando una fecha en el calendario","description":"","id":"automatización-del-componente-jquery-datepicker;reserva-de-una-cita-seleccionando-una-fecha-en-el-calendario","after":[{"result":{"duration":119526000,"status":"passed"},"match":{"location":"com.sqa.datepicker.stepdefinitions.DatepickerStepDefinitions.tearDown()"}}],"type":"scenario","keyword":"Escenario","steps":[{"result":{"duration":1535000,"status":"passed"},"line":12,"name":"el usuario hace clic en el campo de selección de fecha","match":{"location":"com.sqa.datepicker.stepdefinitions.DatepickerStepDefinitions.elUsuarioHaceClicEnElCampoDeSeleccionDeFecha()"},"keyword":"Cuando "},{"result":{"duration":863444000,"status":"passed"},"line":13,"name":"selecciona el día 15 del mes actual","match":{"arguments":[{"val":"15","offset":18}],"location":"com.sqa.datepicker.stepdefinitions.DatepickerStepDefinitions.seleccionaElDiaDelMesActual(int)"},"keyword":"Y "},{"result":{"duration":50216000,"status":"passed"},"line":14,"name":"la fecha seleccionada debe aparecer en el campo de texto","match":{"location":"com.sqa.datepicker.stepdefinitions.DatepickerStepDefinitions.laFechaSeleccionadaDebeAparecerEnElCampoDeTexto()"},"keyword":"Entonces "}],"tags":[{"name":"@scenario1"}]},{"line":7,"name":"","description":"","type":"background","keyword":"Antecedentes","steps":[{"result":{"duration":2318592000,"status":"passed"},"line":8,"name":"que el usuario navega a la página principal de jQuery Datepicker","match":{"location":"com.sqa.datepicker.stepdefinitions.DatepickerStepDefinitions.queElUsuarioNavegaALaPaginaPrincipalDeJQueryDatepicker()"},"keyword":"Dado "}]},{"start_timestamp":"2025-10-06T08:27:17.413Z","before":[{"result":{"duration":683000,"status":"passed"},"match":{"location":"com.sqa.datepicker.stepdefinitions.DatepickerStepDefinitions.setUp()"}}],"line":17,"name":"Selección de una fecha específica en un mes diferente","description":"","id":"automatización-del-componente-jquery-datepicker;selección-de-una-fecha-específica-en-un-mes-diferente","after":[{"result":{"duration":104599000,"status":"passed"},"match":{"location":"com.sqa.datepicker.stepdefinitions.DatepickerStepDefinitions.tearDown()"}}],"type":"scenario","keyword":"Escenario","steps":[{"result":{"duration":894000,"status":"passed"},"line":18,"name":"el usuario hace clic en el campo de selección de fecha","match":{"location":"com.sqa.datepicker.stepdefinitions.DatepickerStepDefinitions.elUsuarioHaceClicEnElCampoDeSeleccionDeFecha()"},"keyword":"Cuando "},{"result":{"duration":856000,"status":"passed"},"line":19,"name":"navega hasta el próximo mes","match":{"location":"com.sqa.datepicker.stepdefinitions.DatepickerStepDefinitions.navegaHastaElProximoMes()"},"keyword":"Y "},{"result":{"duration":698860000,"status":"passed"},"line":20,"name":"selecciona el día 10 del próximo mes","match":{"arguments":[{"val":"10","offset":18}],"location":"com.sqa.datepicker.stepdefinitions.DatepickerStepDefinitions.seleccionaElDiaDelProximoMes(int)"},"keyword":"Y "},{"result":{"duration":20357000,"status":"passed"},"line":21,"name":"la fecha seleccionada debe aparecer en el campo de texto","match":{"location":"com.sqa.datepicker.stepdefinitions.DatepickerStepDefinitions.laFechaSeleccionadaDebeAparecerEnElCampoDeTexto()"},"keyword":"Entonces "}],"tags":[{"name":"@scenario2"}]},{"line":7,"name":"","description":"","type":"background","keyword":"Antecedentes","steps":[{"result":{"duration":2019624000,"status":"passed"},"line":8,"name":"que el usuario navega a la página principal de jQuery Datepicker","match":{"location":"com.sqa.datepicker.stepdefinitions.DatepickerStepDefinitions.queElUsuarioNavegaALaPaginaPrincipalDeJQueryDatepicker()"},"keyword":"Dado "}]},{"start_timestamp":"2025-10-06T08:27:20.570Z","before":[{"result":{"duration":633000,"status":"passed"},"match":{"location":"com.sqa.datepicker.stepdefinitions.DatepickerStepDefinitions.setUp()"}}],"line":24,"name":"Validación de campo bloqueado","description":"","id":"automatización-del-componente-jquery-datepicker;validación-de-campo-bloqueado","after":[{"result":{"duration":124002000,"status":"passed"},"match":{"location":"com.sqa.datepicker.stepdefinitions.DatepickerStepDefinitions.tearDown()"}}],"type":"scenario","keyword":"Escenario","steps":[{"result":{"duration":199609000,"status":"passed"},"line":25,"name":"el usuario intenta ingresar una fecha manualmente en el campo de texto","match":{"location":"com.sqa.datepicker.stepdefinitions.DatepickerStepDefinitions.elUsuarioIntentaIngresarUnaFechaManualmenteEnElCampoDeTexto()"},"keyword":"Cuando "},{"result":{"duration":32110000,"status":"passed"},"line":26,"name":"el campo no debe permitir la edición manual","match":{"location":"com.sqa.datepicker.stepdefinitions.DatepickerStepDefinitions.elCampoNoDebePermitirLaEdicionManual()"},"keyword":"Entonces "},{"result":{"duration":809000,"status":"passed"},"line":27,"name":"solo debe ser posible seleccionar una fecha desde el calendario","match":{"location":"com.sqa.datepicker.stepdefinitions.DatepickerStepDefinitions.soloDebeSerPosibleSeleccionarUnaFechaDesdeElCalendario()"},"keyword":"Y "}],"tags":[{"name":"@scenario3"}]}],"name":"Automatización del componente jQuery Datepicker","description":"  Como usuario del sistema\n  Quiero interactuar con el componente jQuery Datepicker\n  Para seleccionar fechas de manera efectiva","id":"automatización-del-componente-jquery-datepicker","keyword":"Característica","uri":"file:src/test/resources/features/datepicker.feature","tags":[]}]